AUTHORS.rst
CONTRIBUTING.rst
HISTORY.rst
LICENSE
MANIFEST.in
README.rst
requirements.txt
setup.cfg
setup.py
.tox/2.6-nocover/Lib/no-global-site-packages.txt
.tox/2.6-nocover/Lib/orig-prefix.txt
.tox/2.6-nocover/Lib/site-packages/argparse-1.2.1-py2.6.egg-info/SOURCES.txt
.tox/2.6-nocover/Lib/site-packages/argparse-1.2.1-py2.6.egg-info/dependency_links.txt
.tox/2.6-nocover/Lib/site-packages/argparse-1.2.1-py2.6.egg-info/installed-files.txt
.tox/2.6-nocover/Lib/site-packages/argparse-1.2.1-py2.6.egg-info/top_level.txt
.tox/2.6-nocover/Lib/site-packages/colorama-0.3.1-py2.6.egg-info/SOURCES.txt
.tox/2.6-nocover/Lib/site-packages/colorama-0.3.1-py2.6.egg-info/dependency_links.txt
.tox/2.6-nocover/Lib/site-packages/colorama-0.3.1-py2.6.egg-info/installed-files.txt
.tox/2.6-nocover/Lib/site-packages/colorama-0.3.1-py2.6.egg-info/top_level.txt
.tox/2.6-nocover/Lib/site-packages/cov_core-1.14.0-py2.6.egg-info/SOURCES.txt
.tox/2.6-nocover/Lib/site-packages/cov_core-1.14.0-py2.6.egg-info/dependency_links.txt
.tox/2.6-nocover/Lib/site-packages/cov_core-1.14.0-py2.6.egg-info/installed-files.txt
.tox/2.6-nocover/Lib/site-packages/cov_core-1.14.0-py2.6.egg-info/requires.txt
.tox/2.6-nocover/Lib/site-packages/cov_core-1.14.0-py2.6.egg-info/top_level.txt
.tox/2.6-nocover/Lib/site-packages/coverage-3.7.1.dist-info/DESCRIPTION.rst
.tox/2.6-nocover/Lib/site-packages/coverage-3.7.1.dist-info/entry_points.txt
.tox/2.6-nocover/Lib/site-packages/coverage-3.7.1.dist-info/top_level.txt
.tox/2.6-nocover/Lib/site-packages/pip-1.5.2.dist-info/DESCRIPTION.rst
.tox/2.6-nocover/Lib/site-packages/pip-1.5.2.dist-info/entry_points.txt
.tox/2.6-nocover/Lib/site-packages/pip-1.5.2.dist-info/top_level.txt
.tox/2.6-nocover/Lib/site-packages/py-1.4.23-py2.6.egg-info/SOURCES.txt
.tox/2.6-nocover/Lib/site-packages/py-1.4.23-py2.6.egg-info/dependency_links.txt
.tox/2.6-nocover/Lib/site-packages/py-1.4.23-py2.6.egg-info/installed-files.txt
.tox/2.6-nocover/Lib/site-packages/py-1.4.23-py2.6.egg-info/top_level.txt
.tox/2.6-nocover/Lib/site-packages/pytest-2.6.1-py2.6.egg-info/SOURCES.txt
.tox/2.6-nocover/Lib/site-packages/pytest-2.6.1-py2.6.egg-info/dependency_links.txt
.tox/2.6-nocover/Lib/site-packages/pytest-2.6.1-py2.6.egg-info/entry_points.txt
.tox/2.6-nocover/Lib/site-packages/pytest-2.6.1-py2.6.egg-info/installed-files.txt
.tox/2.6-nocover/Lib/site-packages/pytest-2.6.1-py2.6.egg-info/requires.txt
.tox/2.6-nocover/Lib/site-packages/pytest-2.6.1-py2.6.egg-info/top_level.txt
.tox/2.6-nocover/Lib/site-packages/pytest_capturelog-0.7-py2.6.egg-info/SOURCES.txt
.tox/2.6-nocover/Lib/site-packages/pytest_capturelog-0.7-py2.6.egg-info/dependency_links.txt
.tox/2.6-nocover/Lib/site-packages/pytest_capturelog-0.7-py2.6.egg-info/entry_points.txt
.tox/2.6-nocover/Lib/site-packages/pytest_capturelog-0.7-py2.6.egg-info/installed-files.txt
.tox/2.6-nocover/Lib/site-packages/pytest_capturelog-0.7-py2.6.egg-info/requires.txt
.tox/2.6-nocover/Lib/site-packages/pytest_capturelog-0.7-py2.6.egg-info/top_level.txt
.tox/2.6-nocover/Lib/site-packages/pytest_cov-1.8.0-py2.6.egg-info/SOURCES.txt
.tox/2.6-nocover/Lib/site-packages/pytest_cov-1.8.0-py2.6.egg-info/dependency_links.txt
.tox/2.6-nocover/Lib/site-packages/pytest_cov-1.8.0-py2.6.egg-info/entry_points.txt
.tox/2.6-nocover/Lib/site-packages/pytest_cov-1.8.0-py2.6.egg-info/installed-files.txt
.tox/2.6-nocover/Lib/site-packages/pytest_cov-1.8.0-py2.6.egg-info/requires.txt
.tox/2.6-nocover/Lib/site-packages/pytest_cov-1.8.0-py2.6.egg-info/top_level.txt
.tox/2.6-nocover/Lib/site-packages/setuptools-2.2-py2.6.egg-info/SOURCES.txt
.tox/2.6-nocover/Lib/site-packages/setuptools-2.2-py2.6.egg-info/dependency_links.txt
.tox/2.6-nocover/Lib/site-packages/setuptools-2.2-py2.6.egg-info/entry_points.txt
.tox/2.6-nocover/Lib/site-packages/setuptools-2.2-py2.6.egg-info/installed-files.txt
.tox/2.6-nocover/Lib/site-packages/setuptools-2.2-py2.6.egg-info/requires.txt
.tox/2.6-nocover/Lib/site-packages/setuptools-2.2-py2.6.egg-info/top_level.txt
.tox/2.6-nocover/Lib/site-packages/upme-0.2.0-py2.6.egg-info/SOURCES.txt
.tox/2.6-nocover/Lib/site-packages/upme-0.2.0-py2.6.egg-info/dependency_links.txt
.tox/2.6-nocover/Lib/site-packages/upme-0.2.0-py2.6.egg-info/installed-files.txt
.tox/2.6-nocover/Lib/site-packages/upme-0.2.0-py2.6.egg-info/requires.txt
.tox/2.6-nocover/Lib/site-packages/upme-0.2.0-py2.6.egg-info/top_level.txt
.tox/2.6/Lib/no-global-site-packages.txt
.tox/2.6/Lib/orig-prefix.txt
.tox/2.6/Lib/site-packages/argparse-1.2.1-py2.6.egg-info/SOURCES.txt
.tox/2.6/Lib/site-packages/argparse-1.2.1-py2.6.egg-info/dependency_links.txt
.tox/2.6/Lib/site-packages/argparse-1.2.1-py2.6.egg-info/installed-files.txt
.tox/2.6/Lib/site-packages/argparse-1.2.1-py2.6.egg-info/top_level.txt
.tox/2.6/Lib/site-packages/colorama-0.3.1-py2.6.egg-info/SOURCES.txt
.tox/2.6/Lib/site-packages/colorama-0.3.1-py2.6.egg-info/dependency_links.txt
.tox/2.6/Lib/site-packages/colorama-0.3.1-py2.6.egg-info/installed-files.txt
.tox/2.6/Lib/site-packages/colorama-0.3.1-py2.6.egg-info/top_level.txt
.tox/2.6/Lib/site-packages/cov_core-1.14.0-py2.6.egg-info/SOURCES.txt
.tox/2.6/Lib/site-packages/cov_core-1.14.0-py2.6.egg-info/dependency_links.txt
.tox/2.6/Lib/site-packages/cov_core-1.14.0-py2.6.egg-info/installed-files.txt
.tox/2.6/Lib/site-packages/cov_core-1.14.0-py2.6.egg-info/requires.txt
.tox/2.6/Lib/site-packages/cov_core-1.14.0-py2.6.egg-info/top_level.txt
.tox/2.6/Lib/site-packages/coverage-3.7.1.dist-info/DESCRIPTION.rst
.tox/2.6/Lib/site-packages/coverage-3.7.1.dist-info/entry_points.txt
.tox/2.6/Lib/site-packages/coverage-3.7.1.dist-info/top_level.txt
.tox/2.6/Lib/site-packages/pip-1.5.2.dist-info/DESCRIPTION.rst
.tox/2.6/Lib/site-packages/pip-1.5.2.dist-info/entry_points.txt
.tox/2.6/Lib/site-packages/pip-1.5.2.dist-info/top_level.txt
.tox/2.6/Lib/site-packages/py-1.4.23-py2.6.egg-info/SOURCES.txt
.tox/2.6/Lib/site-packages/py-1.4.23-py2.6.egg-info/dependency_links.txt
