Metadata-Version: 1.1
Name: upme
Version: 0.3.0
Summary: Detects outdated packages and updates them inside python scripts
Home-page: https://github.com/storax/upme
Author: David Zuber
Author-email: zuber.david@gmx.de
License: BSD
Keywords: upme
Platform: UNKNOWN
Classifier: Development Status :: 2 - Pre-Alpha
Classifier: Intended Audience :: Developers
Classifier: License :: OSI Approved :: BSD License
Classifier: Natural Language :: English
Classifier: Programming Language :: Python :: 2.7
